{
  "id": "pre-a-06",
  "level": "pre-a",
  "number": 6,
  "title": "Numbers 1–5",
  "titleAr": "الأرقام ١–٥",
  "goal": "Count from one to five",
  "vocab": [
    {
      "en": "one",
      "ar": "واحد",
      "example": "I have one nose."
    },
    {
      "en": "two",
      "ar": "اثنان",
      "example": "I have two eyes."
    },
    {
      "en": "three",
      "ar": "ثلاثة",
      "example": "Three little birds."
    },
    {
      "en": "four",
      "ar": "أربعة",
      "example": "Four big balls."
    },
    {
      "en": "five",
      "ar": "خمسة",
      "example": "Five fingers on my hand."
    }
  ],
  "activities": [
    {
      "type": "vocab"
    },
    {
      "type": "listen-choose",
      "rounds": 5
    },
    {
      "type": "match"
    },
    {
      "type": "quiz",
      "rounds": 4,
      "questions": [
        {
          "q": "How many eyes do you have?",
          "options": [
            "two",
            "one",
            "five",
            "four"
          ],
          "answer": "two"
        }
      ]
    },
    {
      "type": "spell",
      "rounds": 3
    }
  ]
}